{"text":"","historical":"Prior Codifications\n\n1981 Ed., § 1-616.1.\n\n1973 Ed., § 1-345.1.\n\nEmergency Act Amendments\n\nFor temporary repeal of §§ 1-615.01 through 1-615.03, see § 102(b) of the Whistleblower Reinforcement Emergency Amendment Act of 1998 (D.C. Act 12-400, July 13, 1998, 45 DCR 5158) and § 102(b) of the Whistleblower Reinforcement Congressional Review Emergency Amendment Act of 1998 (D.C. Act 12-464, October 28, 1998, 45 DCR 7821).\n\nLegislative History of Laws\n\nFor legislative history of D.C. Law 12-160, see Historical and Statutory Notes following § 1-602.01.\n\nDC CODE § 1-615.01\n\nCurrent through December 11, 2012","credits":"(Mar. 3, 1979, D.C. Law 2-139, § 1501, 25 DCR 5740; Oct. 7, 1998, D.C. Law 12-160, § 102(b), 45 DCR 5147.)","sections":[],"division":{"identifier":"I","text":"Government of District."},"title":{"identifier":"1","text":"Government Organization. (Refs & Annos)"},"chapter":{"identifier":"6","text":"Merit Personnel System."},"subchapter":{"identifier":"XV","text":"Employee Rights and Responsibilities. (Refs & Annos)"},"heading":{"title":"1","chaptersection":"615","identifier":"1-615.01","catch_text":"Declaration of purpose. [Repealed]"}}