{"text":"An attorney for the District of Columbia may not retain attorney fees taxed as costs in litigation in which the District of Columbia is a party.","historical":"Prior Codifications\n\n1981 Ed., § 15-702.\n\n1973 Ed., § 15-702.\n\nDC CODE § 15-702\n\nCurrent through December 11, 2012","credits":"(Dec. 23, 1963, 77 Stat. 531, Pub. L. 88-241, § 1; June 19, 1986, 100 Stat. 633, Pub. L. 99-336, § 4(b)(2).)","sections":[],"division":{"identifier":"II","text":"Judiciary and Judicial Procedure"},"title":{"identifier":"15","text":"Judgments and Executions; Fees and Costs. (Refs & Annos)"},"chapter":{"identifier":"7","text":"Fees and Costs."},"heading":{"title":"15","chaptersection":"702","identifier":"15-702","catch_text":"Attorney fees taxed as costs."}}