{"text":"The provisions of §§ 16-2332 and 16-2333 shall apply to all juvenile case records and juvenile social records as defined therein which are created pursuant to the proceedings under this subchapter.","historical":"Prior Codifications\n\n1981 Ed., § 16-2363.\n\n1973 Ed., § 16-2363.\n\nLegislative History of Laws\n\nFor legislative history of D.C. Law 2-22, see Historical and Statutory Notes following § 16-2301.\n\nFor legislative history of D.C. Law 12-81, see Historical and Statutory Notes following § 16-2301.\n\nDC CODE § 16-2363\n\nCurrent through December 11, 2012","credits":"(Sept. 23, 1977, D.C. Law 2-22, title IV, § 410, 24 DCR 3341; Mar. 24, 1998, D.C. Law 12-81, § 10(ll), 45 DCR 745.)","sections":[],"division":{"identifier":"II","text":"Judiciary and Judicial Procedure"},"title":{"identifier":"16","text":"Particular Actions, Proceedings and Matters. (Refs & Annos)"},"chapter":{"identifier":"23","text":"Family Division Proceedings."},"subchapter":{"identifier":"III","text":"Proceedings Regarding the Termination of Parental Rights of Certain Neglected Children."},"heading":{"title":"16","chaptersection":"2363","identifier":"16-2363","catch_text":"Confidentiality of records."}}