{"text":"On proof of the notice prescribed by section 16-2502, and upon a showing that the court deems satisfactory, the court may change the name of the applicant according to the prayer of the application.","historical":"Prior Codifications\n\n1981 Ed., ยง 16-2503.\n\n1973 Ed., ยง 16-2503.\n\nDC CODE ยง 16-2503\n\nCurrent through December 11, 2012","credits":"(Dec. 23, 1963, 77 Stat. 595, Pub. L. 88-241, ยง 1.)","sections":[],"division":{"identifier":"II","text":"Judiciary and Judicial Procedure"},"title":{"identifier":"16","text":"Particular Actions, Proceedings and Matters. (Refs & Annos)"},"chapter":{"identifier":"25","text":"Change of Name."},"heading":{"title":"16","chaptersection":"2503","identifier":"16-2503","catch_text":"Decree."}}