{"text":"If a question of existence or exercise of jurisdiction under this chapter is raised in a child-custody proceeding, the question, upon request of a party, must be given priority on the calendar and handled expeditiously.","historical":"Legislative History of Laws\n\nFor D.C. Law 13-293, see notes following ยง 16-4601.01.\n\nUniform Law\n\nThis section is based upon ยง 107 of the Uniform Child Custody Jurisdiction and Enforcement Act (1997 Act). See 9, Part IA, Uniform Laws Annotated, Master Edition, or ULA Database on Westlaw.\n\nDC CODE ยง 16-4601.06\n\nCurrent through December 11, 2012","credits":"(Apr. 27, 2001, D.C. Law 13-293, ยง 2(d), 48 DCR 2214.)","sections":[],"division":{"identifier":"II","text":"Judiciary and Judicial Procedure"},"title":{"identifier":"16","text":"Particular Actions, Proceedings and Matters. (Refs & Annos)"},"chapter":{"identifier":"46","text":"Uniform Child-Custody Jurisdiction and Enforcement. (Refs & Annos)"},"subchapter":{"identifier":"I","text":"General Provisions."},"heading":{"title":"16","chaptersection":"4601","identifier":"16-4601.06","catch_text":"Priority."}}