{"text":"A trust may be created only to the extent its purposes are lawful, not contrary to public policy, and possible to achieve. A trust and its terms must be for the benefit of its beneficiaries.","historical":"Legislative History of Laws\n\nFor Law 15-104, see notes following ยง 19-1301.01.\n\nUniform Law\n\nThis section is based upon ยง 404 of the Uniform Trust Code. See 7C, Uniform Laws Annotated, Master Edition, or ULA Database on Westlaw.\n\nDC CODE ยง 19-1304.04\n\nCurrent through December 11, 2012","credits":"(Mar. 10, 2004, D.C. Law 15-104, ยง 2(b), 51 DCR 208.)","sections":[],"division":{"identifier":"III","text":"Decedents' Estates and Fiduciary Relations."},"title":{"identifier":"19","text":"Descent, Distribution, and Trusts. (Refs & Annos)"},"chapter":{"identifier":"13","text":"Uniform Trust Code. (Refs & Annos)"},"subchapter":{"identifier":"IV","text":"Creation, Validity, Modification, and Termination of Trust."},"heading":{"title":"19","chaptersection":"1304","identifier":"19-1304.04","catch_text":"Trust purposes."}}