{"text":"","historical":"Legislative History of Laws\n\nFor Law 14-188, see notes following § 2-1219.29.\n\nFor Law 17-138, see notes following § 2-1219.01.\n\nDC CODE § 2-1219.37\n\nCurrent through December 11, 2012","credits":"(Sept. 11, 1998, D.C. Law 12-144, § 30g, as added Oct. 1, 2002, D.C. Law 14-188, § 2(c), 49 DCR 6516; Mar. 26, 2008, D.C. Law 17-138, § 103(a), 55 DCR 1689.)","sections":[],"division":{"identifier":"I","text":"Government of District."},"title":{"identifier":"2","text":"Government Administration. (Refs & Annos)"},"chapter":{"identifier":"12","text":"Business and Economic Development."},"subchapter":{"identifier":"X","text":"National Capital Revitalization Corporation. [Repealed]"},"part":{"identifier":"B","text":"Rla Revitalization Corporation. [Repealed]"},"heading":{"title":"2","chaptersection":"1219","identifier":"2-1219.37","catch_text":"Reasonable efforts by the Department of Housing and Community Development. [Repealed]"}}