{"text":"","historical":"Emergency Act Amendments\n\nFor temporary (90 day) additions, see § 2(b) to (d) of Mt. Pleasant, Targeted Ward 2, and Ward 6 Single Sales Moratorium Emergency Act of 2008 (D.C. Act 17- 471, July 28, 2008, 55 DCR 9004).\n\nLegislative History of Laws\n\nFor Law 15-187, see notes following § 25-101.\n\nFor Law 17-211, see notes following § 25-342.\n\nFor history of Law 19-171, see notes under § 25-340.\n\nDC CODE § 25-341\n\nCurrent through December 11, 2012","credits":"(Sept. 30, 2004, D.C. Law 15-187, § 101(o), 51 DCR 6525; Aug. 15, 2008, D.C. Law 17-211, § 2(c), 55 DCR 6984; Sept. 26, 2012, D.C. Law 19-171, § 81(b), 59 DCR 6190.)","sections":[],"division":{"identifier":"V","text":"Local Business Affairs"},"title":{"identifier":"25","text":"Alcoholic Beverage Regulation (Refs & Annos)"},"chapter":{"identifier":"3","text":"Requirements to Qualify for License."},"subchapter":{"identifier":"III","text":"Denial of License."},"heading":{"title":"25","chaptersection":"341","identifier":"25-341","catch_text":"Targeted Ward 4 Moratorium Zone. [Repealed]"}}