{"text":"The moneys accumulated from time to time shall be offered to such shareholder or shareholders as shall bid the highest premium for preference or priority of right to an advancement of the ultimate value of 1 or more of his or their respective shares. The said premium shall consist of a percentage on the amount of the advance and shall be deemed to be a consideration or bonus paid by the shareholder for the present and immediate use and possession of the future or ultimate value of the share so advanced, and shall not be deemed usurious. The said premium may either be deducted in advance from the amount to be advanced to the shareholder or be made payable in monthly installments, in addition to legal interest on the sum advanced, as the bylaws may provide.","historical":"Prior Codifications\n\n1981 Ed., ยง 26-507.\n\n1973 Ed., ยง 26-406.\n\nDC CODE ยง 26-207\n\nCurrent through December 11, 2012","credits":"(Mar. 3, 1901, 31 Stat. 1299, ch. 854, ยง 692.)","sections":[],"division":{"identifier":"V","text":"Local Business Affairs"},"title":{"identifier":"26","text":"Banks and Other Financial Institutions. (Refs & Annos)"},"chapter":{"identifier":"2","text":"Building Associations. (Refs & Annos)"},"subchapter":{"identifier":"I","text":"General."},"heading":{"title":"26","chaptersection":"207","identifier":"26-207","catch_text":"Advancements--Payments of premiums."}}