{"text":"At the time of filing an application under this chapter, each applicant shall pay to the Superintendent a non-refundable license fee of $300, except that an applicant for a license to maintain one or more limited stations shall pay the non-refundable limited station license application fee as provided in § 26- 314.","historical":"Prior Codifications\n\n1981 Ed., § 26-1105.\n\nLegislative History of Laws\n\nFor legislative history of D.C. Law 12-111, see Historical and Statutory Notes following § 26-301.\n\nDC CODE § 26-305\n\nCurrent through December 11, 2012","credits":"(May 12, 1998, D.C. Law 12-111, § 6, 45 DCR 1784.)","sections":[],"division":{"identifier":"V","text":"Local Business Affairs"},"title":{"identifier":"26","text":"Banks and Other Financial Institutions. (Refs & Annos)"},"chapter":{"identifier":"3","text":"Check Cashers. (Refs & Annos)"},"heading":{"title":"26","chaptersection":"305","identifier":"26-305","catch_text":"Application and license fees."}}