{"text":"","historical":"Legislative History of Laws\n\nFor history of Law 18-378, see notes under ยง 29-101.01.\n\nDC CODE ยง 29-305.23\n\nCurrent through December 11, 2012","credits":"(July 2, 2011, D.C. Law 18-378, ยง 2, 58 DCR 1720.)","sections":[{"prefix":"a","text":" A corporation may establish a procedure by which the beneficial owner of shares that are registered in the name of a nominee is recognized by the corporation as the shareholder. The extent of this recognition may be determined in the procedure."},{"prefix":"b","text":" The procedure may set forth:"},{"prefix":"1","text":" The types of nominees to which it applies;"},{"prefix":"2","text":" The rights or privileges that the corporation recognizes in a beneficial owner;"},{"prefix":"3","text":" The manner in which the procedure is selected by the nominee;"},{"prefix":"4","text":" The information that must be provided when the procedure is selected;"},{"prefix":"5","text":" The period for which selection of the procedure is effective; and"},{"prefix":"6","text":" Other aspects of the rights and duties created."}],"division":{"identifier":"V","text":"Local Business Affairs"},"title":{"identifier":"29","text":"Business Organizations. (Refs & Annos)"},"chapter":{"identifier":"3","text":"Business Corporations."},"subchapter":{"identifier":"V","text":"Shareholders."},"part":{"identifier":"B","text":"Voting."},"heading":{"title":"29","chaptersection":"305","identifier":"29-305.23","catch_text":"Shares held by nominees."}}