{"text":"A life insurer may lend to a policyholder on the security of the cash surrender value of the policyholder's policy a sum not exceeding the legal reserve that the insurer is required to maintain on the policy.","historical":"Legislative History of Laws\n\nFor Law 14-297, see notes following ยง 31-1371.01.\n\nDC CODE ยง 31-1372.11\n\nCurrent through December 11, 2012","credits":"(Apr. 11, 2003, D.C. Law 14-297, ยง 211, 50 DCR 330.)","sections":[],"division":{"identifier":"V","text":"Local Business Affairs"},"title":{"identifier":"31","text":"Insurance and Securities. (Refs & Annos)"},"subtitle":{"prefix":"II","text":" Regulation of Insurance Industry Generally."},"chapter":{"identifier":"13A","text":"Investments of Insurers."},"subchapter":{"identifier":"II","text":"Life Insurers."},"heading":{"title":"31","chaptersection":"1372","identifier":"31-1372.11","catch_text":"Policy loans."}}