{"text":"If the owner, for the purpose of avoiding the provisions hereof, and defeating the lien of the subcontractor or other person employed by the contractor, as aforesaid, shall make payments to the contractor in advance of the time agreed upon therefor in the contract, and the amount still due or to become due to the contractor shall be insufficient to satisfy the liens of the subcontractors or others so employed by the contractor, the property shall remain subject to said liens in the same manner as if such payments had not been made.","historical":"Prior Codifications\n\n1981 Ed., ยง 38-108.\n\n1973 Ed., ยง 38-108.\n\nDC CODE ยง 40-303.06\n\nCurrent through December 11, 2012","credits":"(Mar. 3, 1901, 31 Stat. 1385, ch. 854, ยง 1244.)","sections":[],"division":{"identifier":"VII","text":"Property."},"title":{"identifier":"40","text":"Liens. (Refs & Annos)"},"chapter":{"identifier":"3","text":"Mechanics, Materialmen, and Contractors. (Refs & Annos)"},"subchapter":{"identifier":"II","text":"Subcontractor's Lien."},"heading":{"title":"40","chaptersection":"303","identifier":"40-303.06","catch_text":"Advance payments."}}