{"text":"","historical":"Legislative History of Laws\n\nFor D.C. Law 14-84, see notes following § 40-301.02.\n\nFor Law 16-31, see notes following § 40-301.03.\n\nDC CODE § 40-303.16a\n\nCurrent through December 11, 2012","credits":"(Mar. 3, 1901, 31 Stat. 1387, c. 854, § 1254a, as added Mar. 19, 2002, D.C. Law 14-84, § 2(d), 49 DCR 198; Oct. 20, 2005, D.C. Law 16-31, § 2(i), 52 DCR 7195.)","sections":[],"division":{"identifier":"VII","text":"Property."},"title":{"identifier":"40","text":"Liens. (Refs & Annos)"},"chapter":{"identifier":"3","text":"Mechanics, Materialmen, and Contractors. (Refs & Annos)"},"subchapter":{"identifier":"II","text":"Subcontractor's Lien."},"heading":{"title":"40","chaptersection":"303","identifier":"40-303.16a","catch_text":"Effect of failure to file notice. [Repealed]"}}