{"text":"Unless the rental agreement specifically provides otherwise and until a lien sale under this chapter, the exclusive care, custody, and control of all personal property stored in the leased self-service storage space shall remain vested in the occupant.","historical":"Legislative History of Laws\n\nFor Law 15-64, see notes following ยง 40-401.\n\nDC CODE ยง 40-405\n\nCurrent through December 11, 2012","credits":"(Feb. 6, 2004, D.C. Law 15-64, ยง 6, 50 DCR 9303.)","sections":[],"division":{"identifier":"VII","text":"Property."},"title":{"identifier":"40","text":"Liens. (Refs & Annos)"},"chapter":{"identifier":"4","text":"Storage Liens."},"heading":{"title":"40","chaptersection":"405","identifier":"40-405","catch_text":"Personal property vested in occupant."}}