{"text":"All amendments and certifications of the condominium instruments shall set forth the instrument number and date of recordation of the declaration and, when necessary, shall set forth the condominium book and page number where the plats and plans are recorded. All condominium instruments and all amendments and certifications thereof shall set forth the name and address of the condominium and shall be so recorded. The Recorder of Deeds shall accept for recordation any executed and acknowledged condominium instrument or any executed and acknowledged amendment and certification without further review of a condominium instrument or the imposition of any additional requirement.","historical":"Prior Codifications\n\n1981 Ed., § 45-1815.\n\n1973 Ed., § 5-1215.\n\nLegislative History of Laws\n\nFor legislative history of D.C. Law 1-89, see Historical and Statutory Notes following § 42-1901.01.\n\nFor legislative history of D.C. Law 8-233, see Historical and Statutory Notes following § 42-1901.07.\n\nDC CODE § 42-1902.05\n\nCurrent through December 11, 2012","credits":"(Mar. 29, 1977, D.C. Law 1-89, title II, § 205, 23 DCR 9532b; Mar. 8, 1991, D.C. Law 8-233, § 2(k), 38 DCR 261.)","sections":[],"division":{"identifier":"VII","text":"Property."},"title":{"identifier":"42","text":"Real Property. (Refs & Annos)"},"subtitle":{"prefix":"III","text":" Condominiums."},"chapter":{"identifier":"19","text":"Condominiums."},"subchapter":{"identifier":"II","text":"Establishment of Condominiums. (Refs & Annos)"},"heading":{"title":"42","chaptersection":"1902","identifier":"42-1902.05","catch_text":"Recordation of condominium instruments; amendment and certification thereof."}}