{"text":"Where a future estate shall be limited to heirs, or issue, or children, posthumous children shall be entitled to take in the same manner as if living at the death of their parent; and a future estate depending on the contingency of the death of any person without heirs, or issue, or children shall be defeated by the birth of a posthumous child of such person.","historical":"Prior Codifications\n\n1981 Ed., ยง 45-404.\n\n1973 Ed., ยง 45-204.\n\nDC CODE ยง 42-704\n\nCurrent through December 11, 2012","credits":"(Mar. 3, 1901, 31 Stat. 1352, ch. 854, ยง 1028.)","sections":[],"division":{"identifier":"VII","text":"Property."},"title":{"identifier":"42","text":"Real Property. (Refs & Annos)"},"subtitle":{"prefix":"I","text":" General."},"chapter":{"identifier":"7","text":"Interpretation of Instruments."},"heading":{"title":"42","chaptersection":"704","identifier":"42-704","catch_text":"Posthumous children."}}