{"text":"Sections 43-101 to 43-114, 43-116 to 43-118, and 43-120 to 43-128 (except § 43-119) shall not be construed to:","historical":"Prior Codifications\n\n1981 Ed., § 27-128.\n\n1973 Ed., § 27-128.\n\nLegislative History of Laws\n\nFor legislative history of D.C. Law 4-34, see Historical and Statutory Notes following § 43-119.\n\nDC CODE § 43-128\n\nCurrent through December 11, 2012","credits":"(Mar. 3, 1901, 31 Stat. 1298, ch. 854, § 686; June 30, 1902, 32 Stat. 534, ch. 1329, § 686; June 25, 1936, 49 Stat. 1921, ch. 804; June 25, 1948, 62 Stat. 991, ch. 646, § 32(a), (b); May 24, 1949, 63 Stat. 107, ch. 139, § 127; July 29, 1970, 84 Stat. 578, Pub. L. 91-358, title I, § 160(a)(2); Oct. 8, 1981, D.C. Law 4-34, § 29(c)(4), 28 DCR 3271.)","sections":[{"prefix":"1","text":" Interfere with or prevent the disinterment of any body in accordance with § 11-2311; or"},{"prefix":"2","text":" Interfere with the disposal of the ashes of bodies which have been cremated."}],"division":{"identifier":"VIII","text":"General Laws."},"title":{"identifier":"43","text":"Cemeteries and Crematories. (Refs & Annos)"},"chapter":{"identifier":"1","text":"Cemetery Associations; Regulatory Provisions."},"heading":{"title":"43","chaptersection":"128","identifier":"43-128","catch_text":"Court-ordered disinterment or disposal of ashes not affected."}}