{"text":"Each corporation shall have power to establish and change bylaws and prescribe rules and regulations for its government and the duties of its officers and the management of its property.","historical":"Prior Codifications\n\n1981 Ed., ยง 27-110.\n\n1973 Ed., ยง 27-110.\n\nDC CODE ยง 43-110\n\nCurrent through December 11, 2012","credits":"(Mar. 3, 1901, 31 Stat. 1295, ch. 854, ยง 666.)","sections":[],"division":{"identifier":"VIII","text":"General Laws."},"title":{"identifier":"43","text":"Cemeteries and Crematories. (Refs & Annos)"},"chapter":{"identifier":"1","text":"Cemetery Associations; Regulatory Provisions."},"heading":{"title":"43","chaptersection":"110","identifier":"43-110","catch_text":"Bylaws."}}