{"text":"","historical":"Prior Codifications\n\n1981 Ed., § 32-609.\n\n1973 Ed., § 32-408.\n\nEffective Dates\n\nSection 11(b) of Pub. L. 98-621 makes § 10 of that act effective on October 1, 1987.\n\nDC CODE § 44-2109\n\nCurrent through December 11, 2012","credits":"(Nov. 7, 1941, 55 Stat. 760, ch. 469, § 1; Reorg. Plan No. 1 (1953), 67 Stat. 631, 18 F.R. 2053, § 5; Nov. 8, 1984, 98 Stat. 3369, Pub. L. 98-621, § 10(j).)","sections":[],"division":{"identifier":"VIII","text":"General Laws."},"title":{"identifier":"44","text":"Charitable and Curative Institutions. (Refs & Annos)"},"subtitle":{"prefix":"V","text":" Repealed Provisions."},"chapter":{"identifier":"21","text":"Saint Elizabeth's Hospital. [Repealed]"},"heading":{"title":"44","chaptersection":"2109","identifier":"44-2109","catch_text":"Gifts to Hospital--Authorization to accept. [Repealed]"}}