{"text":"","historical":"Prior Codifications\n\n1981 Ed., § 47-109.\n\n1973 Ed., § 47-109.\n\nDC CODE § 47-109\n\nCurrent through December 11, 2012","credits":"(June 26, 1934, 48 Stat. 1230, ch. 756, § 14; enacted, Apr. 9, 1997, D.C. Law 11-254, § 2, 44 DCR 1575.)","sections":[{"prefix":"a","text":" On and after July 1, 1935, appropriations for the District of Columbia appearing on the books of the government and listed in subsection (b) of this section are abolished as such, and so much of the several acts as provide for such appropriations is amended so as to authorize in lieu thereof annual definite appropriations, estimates for which shall be incorporated in the estimates of annual appropriations for the District of Columbia."},{"prefix":"b","text":"(1) Refunding water rents, and so forth, District of Columbia (DCx602)."},{"prefix":"2","text":" Refunding taxes, District of Columbia (DCx601)."},{"prefix":"3","text":" Extension, and so forth, of streets and avenues, District of Columbia (fiscal year) (DCx114)."},{"prefix":"4","text":" Policemen and Firemen's Relief Fund, District of Columbia (DCt614)."}],"division":{"identifier":"VIII","text":"General Laws."},"title":{"identifier":"47","text":"Taxation, Licensing, Permits, Assessments, and Fees. (Refs & Annos)"},"chapter":{"identifier":"1","text":"General Provisions."},"heading":{"title":"47","chaptersection":"109","identifier":"47-109","catch_text":"Abolishment of certain federal appropriations."}}