{"text":"The property, real and personal, of the Howard University shall be exempt from taxation so long as such property shall be used only for the purposes set forth in the charter of said institution; provided, that nothing in this section shall exempt any real estate of said University from assessment and liability for special improvements authorized by law; provided also, that this section shall not include any real estate sold or contracted to be sold by said University to any other person than the United States, the title to which may be still in the said University.","historical":"Prior Codifications\n\n1981 Ed., § 47-1018.\n\n1973 Ed., § 47-811.\n\nDC CODE § 47-1018\n\nCurrent through December 11, 2012","credits":"(June 16, 1882, 22 Stat. 105, ch. 222, § 3; enacted, Apr. 9, 1997, D.C. Law 11-254, § 2, 44 DCR 1575.)","sections":[],"division":{"identifier":"VIII","text":"General Laws."},"title":{"identifier":"47","text":"Taxation, Licensing, Permits, Assessments, and Fees. (Refs & Annos)"},"chapter":{"identifier":"10","text":"Property Exempt from Taxation. (Refs & Annos)"},"heading":{"title":"47","chaptersection":"1018","identifier":"47-1018","catch_text":"Howard University."}}