{"text":"The Developer shall work with the Office of Planning and other appropriate agencies prior to and during the zoning process to ensure that the District's planning and other policy objectives and goals, to the extent that the project is not jeopardized financially, are achieved to the fullest extent possible.","historical":"Legislative History of Laws\n\nFor Law 16-278, see notes following ยง 6-1061.01.\n\nDC CODE ยง 6-1062.04\n\nCurrent through December 11, 2012","credits":"(Mar. 14, 2007, D.C. Law 16-278, ยง 204, 54 DCR 895.)","sections":[],"division":{"identifier":"I","text":"Government of District."},"title":{"identifier":"6","text":"Housing and Building Restrictions and Regulations. (Refs & Annos)"},"chapter":{"identifier":"10","text":"Community Development. (Refs & Annos)"},"subchapter":{"identifier":"III-A","text":"Workforce Housing Production Program."},"part":{"identifier":"B","text":"New Town at Capital City Market Development."},"heading":{"title":"6","chaptersection":"1062","identifier":"6-1062.04","catch_text":"Office of Planning."}}