{"text":"This subchapter shall become effective as provided for acts of the Council of the District of Columbia in § 1-206.02(c)(1). Notwithstanding any other provision of law, upon the effective date of this subchapter, all pending applications for permits shall be subject to this subchapter and no outstanding permits shall be renewed or reissued except in accordance with the provisions of this subchapter.","historical":"Prior Codifications\n\n1981 Ed., § 5-1015.\n\n1973 Ed., § 5-835.\n\nLegislative History of Laws\n\nFor legislative history of D.C. Law 2-144, see Historical and Statutory Notes following § 6-1101.\n\nEditor's Notes\n\nBecause of the codification of D.C. Law 5-69 as subchapter II of this chapter, and the designation of the preexisting text of Chapter 11 as subchapter I, \"subchapter\" has been substituted for \"chapter,\" where applicable, in this section.\n\nDC CODE § 6-1115\n\nCurrent through December 11, 2012","credits":"(Mar. 3, 1979, D.C. Law 2-144, § 17, 25 DCR 6939.)","sections":[],"division":{"identifier":"I","text":"Government of District."},"title":{"identifier":"6","text":"Housing and Building Restrictions and Regulations. (Refs & Annos)"},"chapter":{"identifier":"11","text":"Historic Landmark and Historic District Protection."},"subchapter":{"identifier":"I","text":"General Provisions. (Refs & Annos)"},"heading":{"title":"6","chaptersection":"1115","identifier":"6-1115","catch_text":"Effective date."}}