{"text":"","historical":"Prior Codifications\n\n1981 Ed., § 2-1506.\n\n1973 Ed., § 2-276.\n\nLegislative History of Laws\n\nFor Law 17-145, see notes following § 7-1521.01.\n\nUniform Law\n\nThis section is based upon § 6 of the Uniform Anatomical Gift Act (1968 Act). See 8A Uniform Laws Annotated, Master Edition, or ULA Database on WESTLAW.\n\nDC CODE § 7-1521.06\n\nCurrent through December 11, 2012","credits":"(May 26, 1970, 84 Stat. 269, Pub. L. 91-268, § 6; Apr. 15, 2008, D.C. Law 17-145, § 30(d), 55 DCR 2532.)","sections":[],"division":{"identifier":"I","text":"Government of District."},"title":{"identifier":"7","text":"Human Health Care and Safety. (Refs & Annos)"},"subtitle":{"prefix":"F","text":" Anatomical Parts."},"chapter":{"identifier":"15","text":"Anatomical Parts. (Refs & Annos)"},"subchapter":{"identifier":"II","text":"Anatomical Gifts. [Repealed]"},"heading":{"title":"7","chaptersection":"1521","identifier":"7-1521.06","catch_text":"Amendment or revocation of gift. [Repealed]"}}