{"text":"All records and information obtained by the Commission pursuant to this subchapter shall be destroyed by the Commission one year after publication of the Commission's annual report.","historical":"Legislative History of Laws\n\nFor Law 16-262, see notes following ยง 7-2271.01.\n\nDC CODE ยง 7-2271.06\n\nCurrent through December 11, 2012","credits":"(Mar. 14, 2007, D.C. Law 16-262, ยง 206, 54 DCR 794.)","sections":[],"division":{"identifier":"I","text":"Government of District."},"title":{"identifier":"7","text":"Human Health Care and Safety. (Refs & Annos)"},"subtitle":{"prefix":"J","text":" Public Safety."},"chapter":{"identifier":"22","text":"Homeland Security."},"subchapter":{"identifier":"II","text":"District of Columbia Homeland Security Commission."},"heading":{"title":"7","chaptersection":"2271","identifier":"7-2271.06","catch_text":"Records."}}